platzky_google_tag_manager/__init__.py
platzky_google_tag_manager/entrypoint.py
platzky_google_tag_manager-0.1.0.dist-info/LICENSE
platzky_google_tag_manager-0.1.0.dist-info/METADATA
platzky_google_tag_manager-0.1.0.dist-info/WHEEL
platzky_google_tag_manager-0.1.0.dist-info/RECORD
